pixit/__init__.py
pixit/image_manip.py
pixit/datasets/__init__.py
pixit/datasets/load_datasets.py
pixit/datasets/images/animals/africa-animal-animal-photography-2317536.jpg
pixit/datasets/images/animals/africa-animal-animal-photography-68162.jpg
pixit/datasets/images/animals/africa-animal-barbaric-1057366.jpg
pixit/datasets/images/animals/africa-animal-elephant-70080.jpg
pixit/datasets/images/animals/amur-tiger-angry-animal-533055.jpg
pixit/datasets/images/animals/animal-animal-photography-blur-1598343.jpg
pixit/datasets/images/animals/animal-animal-photography-blur-572861.jpg
pixit/datasets/images/animals/animal-animal-photography-carnivore-145899.jpg
pixit/datasets/images/animals/animal-animal-photography-carnivore-792381.jpg
pixit/datasets/images/animals/animal-animal-photography-close-up-802112.jpg
pixit/datasets/images/animals/animal-animal-photography-desert-1598340.jpg
pixit/datasets/images/animals/animal-animal-photography-giraffe-1619507.jpg
pixit/datasets/images/animals/animal-animal-photography-giraffe-67552.jpg
pixit/datasets/images/animals/animal-barbaric-black-and-white-2317537.jpg
pixit/datasets/images/animals/animal-barbaric-brown-1319515.jpg
pixit/datasets/images/animals/animal-blur-close-up-750539.jpg
pixit/datasets/images/animals/animal-ear-elephant-133393.jpg
pixit/datasets/images/animals/animal-elephant-endangered-133394.jpg
pixit/datasets/images/animals/animal-fur-grass-162203.jpg
pixit/datasets/images/animals/animal-grass-savanna-158584.jpg
pixit-0.0.16.dist-info/LICENSE
pixit-0.0.16.dist-info/METADATA
pixit-0.0.16.dist-info/WHEEL
pixit-0.0.16.dist-info/top_level.txt
pixit-0.0.16.dist-info/RECORD
