Metadata-Version: 2.1
Name: pixit
Version: 0.0.16
Summary: Label and annotate images using matplotlib widgets.
Home-page: https://github.com/benrussell80/pixit
Author: Ben Russell
Author-email: bprussell80@gmail.com
License: UNKNOWN
Platform: UNKNOWN
Classifier: Programming Language :: Python :: 3
Classifier: License :: OSI Approved :: MIT License
Classifier: Operating System :: OS Independent
Requires-Dist: sklearn
Requires-Dist: numpy
Requires-Dist: matplotlib
Requires-Dist: smartwidgets
